yapymp4/__init__.py
yapymp4/mp4reader.py
yapymp4/utils.py
yapymp4/version.py
yapymp4-0.0.2a0.dist-info/LICENSE
yapymp4-0.0.2a0.dist-info/METADATA
yapymp4-0.0.2a0.dist-info/WHEEL
yapymp4-0.0.2a0.dist-info/top_level.txt
yapymp4-0.0.2a0.dist-info/RECORD
