Metadata-Version: 2.1
Name: yapymp4
Version: 0.0.2a0
Summary: Implementation of a parser for MP4 in pure python.
Home-page: https://github.com/mylonasc/yapyMP4.git
Author: Charilaos Mylonas
Author-email: mylonas.charilaos@gmail.com
License: UNKNOWN
Platform: UNKNOWN
Classifier: Programming Language :: Python :: 3
Classifier: License :: OSI Approved :: Apache Software License
Classifier: Operating System :: OS Independent
Requires-Python: >=3.6
License-File: LICENSE
